{"1373":{"Z":[["13732","APALACHIN, NY",85,12],["13733","BAINBRIDGE, NY",86,12],["13730","AFTON, NY",86,12],["13736","BERKSHIRE, NY",85,12],["13734","BARTON, NY",85,12],["13731","ANDES, NY",87,12],["13739","BLOOMVILLE, NY",87,12],["13738","BLODGETT MILLS, NY",85,11],["13737","BIBLE SCHOOL PARK, NY",85,12]],"C":[21772,22028,22284,21771]},"1374":{"Z":[["13743","CANDOR, NY",85,12],["13748","CONKLIN, NY",86,12],["13746","CHENANGO FORKS, NY",86,12],["13744","CASTLE CREEK, NY",85,12],["13740","BOVINA CENTER, NY",87,12],["13747","COLLIERSVILLE, NY",87,11],["13749","CORBETTSVILLE, NY",86,12],["13745","CHENANGO BRIDGE, NY",86,12]],"C":[22028,22284,22283,21772]},"1375":{"Z":[["13753","DELHI, NY",87,12],["13754","DEPOSIT, NY",86,12],["13755","DOWNSVILLE, NY",87,12],["13750","DAVENPORT, NY",87,12],["13757","EAST MEREDITH, NY",87,12],["13752","DE LANCEY, NY",87,12],["13756","EAST BRANCH, NY",87,12],["13751","DAVENPORT CENTER, NY",87,12],["13758","EAST PHARSALIA, NY",86,11]],"C":[22284,22028,22027]},"1376":{"Z":[["13760","ENDICOTT, NY",85,12],["13761","ENDICOTT, NY",86,12],["13763","ENDICOTT, NY",86,12],["13762","ENDWELL, NY",86,12]],"C":[21772,22028]},"1377":{"Z":[["13778","GREENE, NY",86,12],["13775","FRANKLIN, NY",87,12],["13777","GLEN AUBREY, NY",85,12],["13776","GILBERTSVILLE, NY",87,12],["13774","FISHS EDDY, NY",87,12]],"C":[21772,22028,22284]},"1378":{"Z":[["13787","HARPURSVILLE, NY",86,12],["13783","HANCOCK, NY",87,12],["13780","GUILFORD, NY",86,12],["13788","HOBART, NY",88,12],["13782","HAMDEN, NY",87,12],["13786","HARPERSFIELD, NY",87,12],["13784","HARFORD, NY",85,12]],"C":[22028,22284,22540,21772]},"1379":{"Z":[["13790","JOHNSON CITY, NY",85,12],["13795","KIRKWOOD, NY",86,12],["13797","LISLE, NY",85,12],["13796","LAURENS, NY",87,11],["13794","KILLAWOG, NY",85,12]],"C":[22028,22283,21772]}}
