{"1470":{"Z":[["14704","JAMESTOWN, NY",79,12],["14701","JAMESTOWN, NY",79,12],["14703","JAMESTOWN, NY",79,12],["14702","JAMESTOWN, NY",80,12],["14706","ALLEGANY, NY",81,12],["14709","ANGELICA, NY",82,12],["14707","ALLENTOWN, NY",82,12],["14708","ALMA, NY",82,12]],"C":[20748,21004,20236,20492]},"1471":{"Z":[["14710","ASHVILLE, NY",79,12],["14719","CATTARAUGUS, NY",80,12],["14712","BEMUS POINT, NY",79,12],["14716","BROCTON, NY",79,12],["14715","BOLIVAR, NY",82,12],["14718","CASSADAGA, NY",80,12],["14711","BELFAST, NY",82,12],["14717","CANEADEA, NY",81,12],["14714","BLACK CREEK, NY",81,12]],"C":[20236,20492,21004,20748]},"1472":{"Z":[["14727","CUBA, NY",81,12],["14724","CLYMER, NY",79,12],["14726","CONEWANGO VALLEY, NY",80,12],["14723","CHERRY CREEK, NY",79,12],["14728","DEWITTVILLE, NY",79,12],["14729","EAST OTTO, NY",80,12],["14720","CELORON, NY",80,12],["14721","CERES, NY",81,12],["14722","CHAUTAUQUA, NY",79,12]],"C":[20748,20236,20492]},"1473":{"Z":[["14737","FRANKLINVILLE, NY",81,12],["14733","FALCONER, NY",80,12],["14738","FREWSBURG, NY",80,12],["14739","FRIENDSHIP, NY",82,12],["14735","FILLMORE, NY",82,12],["14731","ELLICOTTVILLE, NY",81,12],["14736","FINDLEY LAKE, NY",79,12],["14732","ELLINGTON, NY",80,12],["14730","EAST RANDOLPH, NY",80,12]],"C":[20748,20492,21004,20236]},"1474":{"Z":[["14747","KENNEDY, NY",80,12],["14744","HOUGHTON, NY",81,12],["14741","GREAT VALLEY, NY",81,12],["14743","HINSDALE, NY",81,12],["14740","GERRY, NY",80,12],["14748","KILL BUCK, NY",81,12],["14742","GREENHURST, NY",79,12],["14745","HUME, NY",82,12]],"C":[20492,20748,20236,21004]},"1475":{"Z":[["14750","LAKEWOOD, NY",79,12],["14757","MAYVILLE, NY",79,12],["14755","LITTLE VALLEY, NY",80,12],["14753","LIMESTONE, NY",81,12],["14754","LITTLE GENESEE, NY",81,12],["14752","LILY DALE, NY",79,12],["14756","MAPLE SPRINGS, NY",79,12],["14751","LEON, NY",80,12],["14758","NIOBE, NY",79,12]],"C":[20236,20492,20748]},"1476":{"Z":[["14760","OLEAN, NY",81,12],["14767","PANAMA, NY",79,12],["14769","PORTLAND, NY",79,12],["14766","OTTO, NY",80,12]],"C":[20748,20236,20492]},"1477":{"Z":[["14779","SALAMANCA, NY",81,12],["14772","RANDOLPH, NY",80,12],["14770","PORTVILLE, NY",81,12],["14775","RIPLEY, NY",79,12],["14778","SAINT BONAVENTURE, NY",81,12],["14777","RUSHFORD, NY",81,12],["14774","RICHBURG, NY",81,12],["14776","ROSSBURG, NY",82,12]],"C":[20748,20492,20236,21004]},"1478":{"Z":[["14787","WESTFIELD, NY",79,12],["14782","SINCLAIRVILLE, NY",80,12],["14781","SHERMAN, NY",79,12],["14784","STOCKTON, NY",79,12],["14783","STEAMBURG, NY",80,12],["14788","WESTONS MILLS, NY",81,12],["14786","WEST CLARKSVILLE, NY",81,12],["14785","STOW, NY",79,12]],"C":[20236,20492,20748]}}
