{"3420":{"Z":[["34201","BRADENTON, FL",74,38],["34202","BRADENTON, FL",74,38],["34203","BRADENTON, FL",74,38],["34206","BRADENTON, FL",74,38],["34204","BRADENTON, FL",74,38],["34205","BRADENTON, FL",74,38],["34208","BRADENTON, FL",74,38],["34207","BRADENTON, FL",74,38],["34209","BRADENTON, FL",74,38]],"C":[18982]},"3421":{"Z":[["34210","BRADENTON, FL",74,38],["34219","PARRISH, FL",74,38],["34217","BRADENTON BEACH, FL",74,38],["34216","ANNA MARIA, FL",73,38],["34215","CORTEZ, FL",74,38],["34218","HOLMES BEACH, FL",74,38]],"C":[18982,18726]},"3422":{"Z":[["34221","PALMETTO, FL",74,38],["34220","PALMETTO, FL",74,38],["34223","ENGLEWOOD, FL",74,38],["34224","ENGLEWOOD, FL",74,39],["34222","ELLENTON, FL",74,38],["34229","OSPREY, FL",74,38],["34228","LONGBOAT KEY, FL",74,38]],"C":[18982,18983]},"3423":{"Z":[["34230","SARASOTA, FL",74,38],["34231","SARASOTA, FL",74,38],["34235","SARASOTA, FL",74,38],["34236","SARASOTA, FL",74,38],["34237","SARASOTA, FL",74,38],["34238","SARASOTA, FL",74,38],["34239","SARASOTA, FL",74,38],["34233","SARASOTA, FL",74,38],["34234","SARASOTA, FL",74,38],["34232","SARASOTA, FL",74,38]],"C":[18982]},"3424":{"Z":[["34240","SARASOTA, FL",74,38],["34241","SARASOTA, FL",74,38],["34243","SARASOTA, FL",74,38],["34242","SARASOTA, FL",74,38]],"C":[18982]},"3425":{"Z":[["34251","MYAKKA CITY, FL",74,38],["34250","TERRA CEIA, FL",74,38]],"C":[18982]},"3426":{"Z":[["34266","ARCADIA, FL",75,38],["34265","ARCADIA, FL",75,38],["34268","NOCATEE, FL",75,38],["34264","ONECO, FL",74,38],["34260","MANASOTA, FL",74,38],["34267","FORT OGDEN, FL",75,38]],"C":[18982,19238]},"3427":{"Z":[["34277","SARASOTA, FL",74,38],["34276","SARASOTA, FL",74,38],["34278","SARASOTA, FL",74,38],["34274","NOKOMIS, FL",74,38],["34275","NOKOMIS, FL",74,38],["34272","LAUREL, FL",74,38],["34270","TALLEVAST, FL",74,38]],"C":[18982]},"3428":{"Z":[["34281","BRADENTON, FL",74,38],["34282","BRADENTON, FL",74,38],["34280","BRADENTON, FL",74,38],["34284","VENICE, FL",74,38],["34285","VENICE, FL",74,39],["34286","NORTH PORT, FL",74,39],["34287","NORTH PORT, FL",74,38]],"C":[18983,18982]},"3429":{"Z":[["34292","VENICE, FL",74,39],["34293","VENICE, FL",74,39],["34295","ENGLEWOOD, FL",74,39]],"C":[18983]}}
