{"3790":{"Z":[["37909","KNOXVILLE, TN",71,23],["37902","KNOXVILLE, TN",71,23],["37901","KNOXVILLE, TN",71,23]],"C":[18199]},"3791":{"Z":[["37919","KNOXVILLE, TN",71,23],["37918","KNOXVILLE, TN",71,23],["37917","KNOXVILLE, TN",71,23],["37916","KNOXVILLE, TN",71,23],["37915","KNOXVILLE, TN",71,23],["37912","KNOXVILLE, TN",71,23],["37914","KNOXVILLE, TN",72,23]],"C":[18199,18455]},"3792":{"Z":[["37923","KNOXVILLE, TN",71,23],["37929","KNOXVILLE, TN",72,23],["37922","KNOXVILLE, TN",71,23],["37920","KNOXVILLE, TN",71,23],["37927","KNOXVILLE, TN",71,23],["37924","KNOXVILLE, TN",71,23],["37921","KNOXVILLE, TN",71,23],["37928","KNOXVILLE, TN",71,23]],"C":[18199,18455]},"3793":{"Z":[["37933","KNOXVILLE, TN",71,23],["37939","KNOXVILLE, TN",71,23],["37938","KNOXVILLE, TN",71,23],["37932","KNOXVILLE, TN",71,23],["37931","KNOXVILLE, TN",71,23],["37930","KNOXVILLE, TN",71,23]],"C":[18199]},"3794":{"Z":[["37940","KNOXVILLE, TN",71,23]],"C":[18199]},"3795":{"Z":[["37950","KNOXVILLE, TN",71,23]],"C":[18199]},"3799":{"Z":[["37999","KNOXVILLE, TN",71,23],["37997","KNOXVILLE, TN",71,23],["37998","KNOXVILLE, TN",72,23],["37996","KNOXVILLE, TN",71,23],["37995","KNOXVILLE, TN",71,23],["37990","KNOXVILLE, TN",71,23]],"C":[18199,18455]}}
