{"3840":{"Z":[["38401","COLUMBIA, TN",66,24],["38402","COLUMBIA, TN",66,24]],"C":[16920]},"3842":{"Z":[["38425","CLIFTON, TN",64,24]],"C":[16408]},"3844":{"Z":[["38449","ARDMORE, TN",66,25]],"C":[16921]},"3845":{"Z":[["38451","CULLEOKA, TN",66,24],["38456","ETHRIDGE, TN",65,24],["38450","COLLINWOOD, TN",65,24],["38454","DUCK RIVER, TN",65,23],["38452","CYPRESS INN, TN",65,24],["38457","FIVE POINTS, TN",65,25],["38459","FRANKEWING, TN",66,24],["38453","DELLROSE, TN",66,24],["38455","ELKTON, TN",66,25]],"C":[16665,16921,16920,16664,16663]},"3846":{"Z":[["38464","LAWRENCEBURG, TN",65,24],["38462","HOHENWALD, TN",65,24],["38468","LEOMA, TN",65,24],["38469","LORETTO, TN",65,25],["38463","IRON CITY, TN",65,25],["38460","GOODSPRING, TN",66,25],["38461","HAMPSHIRE, TN",65,24]],"C":[16664,16665,16921]},"3847":{"Z":[["38478","PULASKI, TN",66,24],["38474","MOUNT PLEASANT, TN",66,24],["38477","PROSPECT, TN",66,24],["38472","LYNNVILLE, TN",66,24],["38476","PRIMM SPRINGS, TN",66,23],["38473","MINOR HILL, TN",66,25],["38475","OLIVEHILL, TN",64,24],["38471","LUTTS, TN",64,25]],"C":[16920,16919,16921,16408,16409]},"3848":{"Z":[["38485","WAYNESBORO, TN",65,24],["38483","SUMMERTOWN, TN",65,24],["38488","TAFT, TN",66,25],["38482","SANTA FE, TN",66,23],["38487","WILLIAMSPORT, TN",66,23],["38486","WESTPOINT, TN",65,24],["38481","SAINT JOSEPH, TN",65,25]],"C":[16664,16921,16919,16665]}}
