{"770":{"Z":[["77058","HOUSTON, TX",52,34],["77011","HOUSTON, TX",51,34],["77012","HOUSTON, TX",51,34],["77013","HOUSTON, TX",51,34],["77014","HOUSTON, TX",51,34],["77015","HOUSTON, TX",51,34],["77016","HOUSTON, TX",51,34],["77017","HOUSTON, TX",51,34],["77018","HOUSTON, TX",51,34],["77019","HOUSTON, TX",51,34]],"C":[13346,13090]},"772":{"Z":[["77201","HOUSTON, TX",51,34],["77299","HOUSTON, TX",51,34],["77298","HOUSTON, TX",51,34],["77297","HOUSTON, TX",51,34],["77293","HOUSTON, TX",51,34],["77292","HOUSTON, TX",51,34],["77291","HOUSTON, TX",51,34],["77290","HOUSTON, TX",51,34],["77289","HOUSTON, TX",51,34],["77288","HOUSTON, TX",51,34]],"C":[13090,13346]},"773":{"Z":[["77383","SPRING, TX",51,34],["77373","SPRING, TX",51,34],["77381","SPRING, TX",51,33],["77386","SPRING, TX",51,33],["77387","SPRING, TX",51,33],["77379","SPRING, TX",51,34],["77388","SPRING, TX",51,34],["77393","SPRING, TX",51,33],["77391","SPRING, TX",51,34],["77382","SPRING, TX",51,34]],"C":[13344,12833,13601,13090,13089,13088,13345]},"774":{"Z":[["77449","KATY, TX",51,34],["77493","KATY, TX",51,34],["77492","KATY, TX",51,34],["77491","KATY, TX",51,34],["77494","KATY, TX",51,34],["77450","KATY, TX",51,34],["77410","CYPRESS, TX",51,34],["77429","CYPRESS, TX",51,34],["77433","CYPRESS, TX",51,34],["77496","SUGAR LAND, TX",51,34]],"C":[12835,12833,13090,13091,12834,13092,12579,12836,12578]},"775":{"Z":[["77503","PASADENA, TX",52,34],["77501","PASADENA, TX",51,34],["77505","PASADENA, TX",52,34],["77504","PASADENA, TX",52,34],["77506","PASADENA, TX",52,34],["77502","PASADENA, TX",52,34],["77507","PASADENA, TX",52,34],["77508","PASADENA, TX",52,34],["77581","PEARLAND, TX",51,35],["77588","PEARLAND, TX",51,34]],"C":[13090,13091,13347,13345,13602,13601,13346]},"776":{"Z":[["77640","PORT ARTHUR, TX",54,34],["77641","PORT ARTHUR, TX",53,34],["77643","PORT ARTHUR, TX",54,33],["77642","PORT ARTHUR, TX",54,34],["77630","ORANGE, TX",54,33],["77631","ORANGE, TX",54,33],["77632","ORANGE, TX",54,33],["77662","VIDOR, TX",54,33],["77670","VIDOR, TX",54,33],["77627","NEDERLAND, TX",53,33]],"C":[13858,13602,13857,13601,13600,13856]},"777":{"Z":[["77725","BEAUMONT, TX",53,34],["77702","BEAUMONT, TX",53,33],["77703","BEAUMONT, TX",53,33],["77704","BEAUMONT, TX",53,33],["77706","BEAUMONT, TX",53,33],["77708","BEAUMONT, TX",53,33],["77713","BEAUMONT, TX",53,33],["77726","BEAUMONT, TX",53,33],["77705","BEAUMONT, TX",53,34],["77710","BEAUMONT, TX",53,34]],"C":[13602,13601]},"778":{"Z":[["77842","COLLEGE STATION, TX",50,32],["77843","COLLEGE STATION, TX",50,32],["77844","COLLEGE STATION, TX",50,32],["77841","COLLEGE STATION, TX",50,32],["77845","COLLEGE STATION, TX",50,32],["77840","COLLEGE STATION, TX",50,32],["77803","BRYAN, TX",49,32],["77801","BRYAN, TX",50,32],["77808","BRYAN, TX",50,32],["77806","BRYAN, TX",50,32]],"C":[12832,12576,12833,12577,12831]},"779":{"Z":[["77904","VICTORIA, TX",48,35],["77901","VICTORIA, TX",48,36],["77905","VICTORIA, TX",48,36],["77902","VICTORIA, TX",48,35],["77903","VICTORIA, TX",48,36],["77979","PORT LAVACA, TX",49,36],["77954","CUERO, TX",48,35],["77995","YOAKUM, TX",48,35],["77957","EDNA, TX",49,35],["77964","HALLETTSVILLE, TX",49,34]],"C":[12323,12324,12580,12579,12578,12322]}}
