{"9340":{"Z":[["93403","SAN LUIS OBISPO, CA",7,24],["93407","SAN LUIS OBISPO, CA",7,24],["93409","SAN LUIS OBISPO, CA",7,24],["93406","SAN LUIS OBISPO, CA",7,24],["93405","SAN LUIS OBISPO, CA",7,24],["93401","SAN LUIS OBISPO, CA",7,24],["93408","SAN LUIS OBISPO, CA",7,24],["93402","LOS OSOS, CA",7,24]],"C":[1816]},"9341":{"Z":[["93410","SAN LUIS OBISPO, CA",7,24],["93412","LOS OSOS, CA",7,24]],"C":[1816]},"9342":{"Z":[["93422","ATASCADERO, CA",7,24],["93423","ATASCADERO, CA",7,24],["93420","ARROYO GRANDE, CA",7,24],["93421","ARROYO GRANDE, CA",7,24],["93428","CAMBRIA, CA",6,24],["93427","BUELLTON, CA",8,25],["93426","BRADLEY, CA",6,23],["93424","AVILA BEACH, CA",7,24],["93429","CASMALIA, CA",7,25]],"C":[1817,1816,1560,2073,1559]},"9343":{"Z":[["93438","LOMPOC, CA",8,26],["93437","LOMPOC, CA",7,25],["93436","LOMPOC, CA",7,25],["93433","GROVER BEACH, CA",7,24],["93434","GUADALUPE, CA",7,25],["93430","CAYUCOS, CA",6,24],["93432","CRESTON, CA",7,24],["93435","HARMONY, CA",6,24]],"C":[2074,1817,1816,1560]},"9344":{"Z":[["93447","PASO ROBLES, CA",7,23],["93446","PASO ROBLES, CA",7,24],["93444","NIPOMO, CA",7,25],["93442","MORRO BAY, CA",7,24],["93443","MORRO BAY, CA",7,24],["93448","PISMO BEACH, CA",7,24],["93449","PISMO BEACH, CA",7,24],["93445","OCEANO, CA",7,24],["93440","LOS ALAMOS, CA",8,25],["93441","LOS OLIVOS, CA",8,25]],"C":[2073,1815,1816,1817]},"9345":{"Z":[["93457","SANTA MARIA, CA",7,25],["93456","SANTA MARIA, CA",8,25],["93455","SANTA MARIA, CA",7,25],["93458","SANTA MARIA, CA",7,25],["93454","SANTA MARIA, CA",7,25],["93451","SAN MIGUEL, CA",7,23],["93453","SANTA MARGARITA, CA",8,24],["93450","SAN ARDO, CA",7,23],["93452","SAN SIMEON, CA",6,24]],"C":[1817,2073,1815,2072,1560]},"9346":{"Z":[["93465","TEMPLETON, CA",7,24],["93464","SOLVANG, CA",8,25],["93463","SOLVANG, CA",8,25],["93460","SANTA YNEZ, CA",8,25],["93461","SHANDON, CA",8,24]],"C":[2072,1816,2073]},"9348":{"Z":[["93483","GROVER BEACH, CA",7,24]],"C":[1816]}}
