{"9390":{"Z":[["93907","SALINAS, CA",5,22],["93908","SALINAS, CA",5,22],["93905","SALINAS, CA",5,22],["93901","SALINAS, CA",6,22],["93902","SALINAS, CA",6,22],["93906","SALINAS, CA",5,22]],"C":[1302,1558]},"9391":{"Z":[["93915","SALINAS, CA",6,22],["93912","SALINAS, CA",6,22]],"C":[1558]},"9392":{"Z":[["93927","GREENFIELD, CA",6,22],["93923","CARMEL, CA",5,22],["93922","CARMEL, CA",5,22],["93921","CARMEL, CA",5,22],["93926","GONZALES, CA",6,22],["93924","CARMEL VALLEY, CA",5,22],["93925","CHUALAR, CA",5,22],["93928","JOLON, CA",6,23]],"C":[1558,1302,1559]},"9393":{"Z":[["93933","MARINA, CA",5,22],["93930","KING CITY, CA",6,23],["93932","LOCKWOOD, CA",6,23]],"C":[1302,1559]},"9394":{"Z":[["93940","MONTEREY, CA",5,22],["93943","MONTEREY, CA",6,22],["93942","MONTEREY, CA",6,22],["93944","MONTEREY, CA",5,22]],"C":[1302,1558]},"9395":{"Z":[["93955","SEASIDE, CA",5,22],["93950","PACIFIC GROVE, CA",5,22],["93953","PEBBLE BEACH, CA",5,22],["93954","SAN LUCAS, CA",6,22]],"C":[1302,1558]},"9396":{"Z":[["93960","SOLEDAD, CA",6,22],["93962","SPRECKELS, CA",5,22]],"C":[1558,1302]}}
