{"5670":{"Z":[["56701","THIEF RIVER FALLS, MN",50,2]],"C":[12802]},"5671":{"Z":[["56716","CROOKSTON, MN",49,2],["56713","ARGYLE, MN",49,1],["56710","ALVARADO, MN",48,1],["56715","BROOKS, MN",50,2],["56711","ANGLE INLET, MN",52,0],["56712","ANGUS, MN",50,2]],"C":[12289,12802,13312,12546,12545]},"5672":{"Z":[["56721","EAST GRAND FORKS, MN",49,2],["56725","GOODRIDGE, MN",51,2],["56723","FISHER, MN",49,2],["56727","GRYGLA, MN",50,1],["56722","EUCLID, MN",50,2],["56724","GATZKE, MN",50,1]],"C":[12546,13058,12801,12802]},"5673":{"Z":[["56738","NEWFOLDEN, MN",50,1],["56732","KARLSTAD, MN",49,1],["56736","MENTOR, MN",50,2],["56737","MIDDLE RIVER, MN",49,1],["56733","KENNEDY, MN",49,1]],"C":[12801,12545,12802]},"5674":{"Z":[["56742","OKLEE, MN",50,2],["56748","PLUMMER, MN",50,2],["56744","OSLO, MN",48,1],["56741","OAK ISLAND, MN",52,0]],"C":[12802,12289,13312]},"5675":{"Z":[["56750","RED LAKE FALLS, MN",50,2],["56757","STEPHEN, MN",49,1],["56756","SALOL, MN",51,0],["56754","SAINT HILAIRE, MN",50,2],["56758","STRANDQUIST, MN",50,1],["56755","SAINT VINCENT, MN",48,0]],"C":[13056,12801,12288,12802,12545]},"5676":{"Z":[["56763","WARROAD, MN",51,0],["56762","WARREN, MN",49,1],["56761","WANNASKA, MN",51,0],["56760","VIKING, MN",50,1]],"C":[13056,12545,12801]}}
