{"4730":{"Z":[["47302","MUNCIE, IN",69,16],["47303","MUNCIE, IN",69,15],["47304","MUNCIE, IN",69,15],["47306","MUNCIE, IN",69,16],["47305","MUNCIE, IN",69,15],["47308","MUNCIE, IN",69,15],["47307","MUNCIE, IN",69,16]],"C":[17680,17679]},"4732":{"Z":[["47327","CAMBRIDGE CITY, IN",69,16],["47320","ALBANY, IN",69,15],["47326","BRYANT, IN",70,15],["47325","BROWNSVILLE, IN",70,16],["47324","BOSTON, IN",70,16],["47322","BENTONVILLE, IN",69,16]],"C":[17680,17679,17935,17936]},"4733":{"Z":[["47331","CONNERSVILLE, IN",69,16],["47330","CENTERVILLE, IN",70,16],["47336","DUNKIRK, IN",69,15],["47334","DALEVILLE, IN",69,16],["47338","EATON, IN",69,15],["47335","DUBLIN, IN",69,16],["47339","ECONOMY, IN",69,16],["47337","DUNREITH, IN",69,16]],"C":[17680,17936,17679]},"4734":{"Z":[["47348","HARTFORD CITY, IN",69,15],["47346","HAGERSTOWN, IN",69,16],["47340","FARMLAND, IN",69,16],["47342","GASTON, IN",69,15],["47341","FOUNTAIN CITY, IN",70,16],["47345","GREENS FORK, IN",69,16],["47344","GREENSBORO, IN",69,16]],"C":[17936,17679,17680]},"4735":{"Z":[["47353","LIBERTY, IN",70,17],["47356","MIDDLETOWN, IN",69,16],["47359","MONTPELIER, IN",69,15],["47355","LYNN, IN",70,16],["47357","MILTON, IN",69,16],["47354","LOSANTVILLE, IN",69,16],["47358","MODOC, IN",69,16],["47352","LEWISVILLE, IN",69,16],["47351","KENNARD, IN",69,16]],"C":[17936,17937,17680,17679]},"4736":{"Z":[["47362","NEW CASTLE, IN",69,16],["47368","PARKER CITY, IN",69,16],["47360","MOORELAND, IN",69,16],["47369","PENNVILLE, IN",69,15],["47367","OAKVILLE, IN",69,16],["47361","MOUNT SUMMIT, IN",69,16],["47366","NEW LISBON, IN",69,16]],"C":[17680,17679]},"4737":{"Z":[["47374","RICHMOND, IN",69,16],["47375","RICHMOND, IN",69,16],["47371","PORTLAND, IN",70,15],["47373","REDKEY, IN",69,15],["47370","PERSHING, IN",69,16]],"C":[17680,17935,17679]},"4738":{"Z":[["47383","SELMA, IN",69,16],["47380","RIDGEVILLE, IN",69,16],["47384","SHIRLEY, IN",69,16],["47385","SPICELAND, IN",69,16],["47386","SPRINGPORT, IN",69,16],["47387","STRAUGHN, IN",69,16],["47388","SULPHUR SPRINGS, IN",69,16],["47382","SARATOGA, IN",70,15],["47381","SALAMONIA, IN",70,15]],"C":[17680,17935]},"4739":{"Z":[["47394","WINCHESTER, IN",70,16],["47396","YORKTOWN, IN",69,16],["47390","UNION CITY, IN",69,16],["47393","WILLIAMSBURG, IN",69,16],["47392","WEBSTER, IN",70,16]],"C":[17680,17936]}}
