{"2010":{"Z":[["20109","MANASSAS, VA",83,18],["20108","MANASSAS, VA",83,18],["20105","ALDIE, VA",82,18],["20106","AMISSVILLE, VA",82,18],["20104","DULLES, VA",82,17],["20102","DULLES, VA",82,17],["20107","ARCOLA, VA",83,18],["20103","DULLES, VA",83,18],["20101","DULLES, VA",83,18]],"C":[21266,21010,21009]},"2011":{"Z":[["20110","MANASSAS, VA",83,18],["20113","MANASSAS, VA",83,18],["20112","MANASSAS, VA",83,18],["20111","MANASSAS, VA",83,18],["20115","MARSHALL, VA",82,18],["20116","MARSHALL, VA",82,18],["20119","CATLETT, VA",82,18],["20117","MIDDLEBURG, VA",82,18],["20118","MIDDLEBURG, VA",82,18]],"C":[21266,21010]},"2012":{"Z":[["20121","CENTREVILLE, VA",83,18],["20122","CENTREVILLE, VA",83,18],["20120","CENTREVILLE, VA",83,18],["20124","CLIFTON, VA",83,18],["20129","PAEONIAN SPRINGS, VA",82,17],["20128","ORLEAN, VA",82,18]],"C":[21266,21009,21010]},"2013":{"Z":[["20136","BRISTOW, VA",83,18],["20134","PURCELLVILLE, VA",82,17],["20132","PURCELLVILLE, VA",82,17],["20137","BROAD RUN, VA",82,18],["20130","PARIS, VA",82,18],["20139","CASANOVA, VA",82,18],["20135","BLUEMONT, VA",82,17],["20138","CALVERTON, VA",82,18],["20131","PHILOMONT, VA",82,18]],"C":[21010,21266,21009]},"2014":{"Z":[["20148","ASHBURN, VA",83,18],["20147","ASHBURN, VA",83,18],["20146","ASHBURN, VA",82,17],["20149","ASHBURN, VA",82,17],["20141","ROUND HILL, VA",82,17],["20142","ROUND HILL, VA",82,17],["20143","CATHARPIN, VA",83,18],["20144","DELAPLANE, VA",82,18],["20140","RECTORTOWN, VA",82,18]],"C":[21266,21009,21010]},"2015":{"Z":[["20153","CHANTILLY, VA",83,18],["20151","CHANTILLY, VA",83,18],["20152","CHANTILLY, VA",83,18],["20156","GAINESVILLE, VA",83,18],["20155","GAINESVILLE, VA",82,18],["20159","HAMILTON, VA",82,17],["20158","HAMILTON, VA",82,17]],"C":[21266,21010,21009]},"2016":{"Z":[["20166","STERLING, VA",83,18],["20164","STERLING, VA",83,18],["20165","STERLING, VA",83,18],["20163","STERLING, VA",82,17],["20167","STERLING, VA",82,17],["20169","HAYMARKET, VA",82,18],["20168","HAYMARKET, VA",83,18],["20160","LINCOLN, VA",82,17]],"C":[21266,21009,21010]},"2017":{"Z":[["20171","HERNDON, VA",83,18],["20172","HERNDON, VA",83,18],["20170","HERNDON, VA",83,18],["20178","LEESBURG, VA",82,17],["20177","LEESBURG, VA",82,17],["20176","LEESBURG, VA",82,17],["20175","LEESBURG, VA",82,18]],"C":[21266,21009,21010]},"2018":{"Z":[["20188","WARRENTON, VA",82,18],["20186","WARRENTON, VA",82,18],["20187","WARRENTON, VA",82,18],["20182","NOKESVILLE, VA",83,18],["20181","NOKESVILLE, VA",83,18],["20180","LOVETTSVILLE, VA",82,17],["20184","UPPERVILLE, VA",82,18],["20185","UPPERVILLE, VA",82,18]],"C":[21010,21266,21009]},"2019":{"Z":[["20192","HERNDON, VA",83,18],["20193","RESTON, VA",83,18],["20190","RESTON, VA",83,18],["20191","RESTON, VA",83,18],["20195","RESTON, VA",83,18],["20194","RESTON, VA",83,18],["20196","RESTON, VA",83,18],["20198","THE PLAINS, VA",82,18],["20197","WATERFORD, VA",82,17],["20199","DULLES, VA",82,17]],"C":[21266,21010,21009]}}
