{"0290":{"Z":[["02905","PROVIDENCE, RI",93,13],["02901","PROVIDENCE, RI",93,13],["02902","PROVIDENCE, RI",93,13],["02903","PROVIDENCE, RI",93,13],["02909","PROVIDENCE, RI",93,13],["02908","PROVIDENCE, RI",93,13],["02907","PROVIDENCE, RI",93,13],["02906","PROVIDENCE, RI",93,13],["02904","PROVIDENCE, RI",93,13]],"C":[23821]},"0291":{"Z":[["02918","PROVIDENCE, RI",93,13],["02912","PROVIDENCE, RI",93,13],["02910","CRANSTON, RI",93,13],["02919","JOHNSTON, RI",93,13],["02914","EAST PROVIDENCE, RI",93,13],["02915","RIVERSIDE, RI",93,13],["02911","NORTH PROVIDENCE, RI",93,13],["02917","SMITHFIELD, RI",93,13],["02916","RUMFORD, RI",93,13]],"C":[23821]},"0292":{"Z":[["02921","CRANSTON, RI",93,13],["02920","CRANSTON, RI",93,13]],"C":[23821]},"0294":{"Z":[["02940","PROVIDENCE, RI",93,13]],"C":[23821]}}
